sarsolver/__init__.py
sarsolver/sarsolver_cxx.cpython-312-x86_64-linux-musl.so
sarsolver/base/__init__.py
sarsolver/base/hypothesis.py
sarsolver/base/measurement.py
sarsolver/cil/__init__.py
sarsolver/cil/base.py
sarsolver/cil/hypothesis.py
sarsolver/cil/measurement.py
sarsolver/cil/operator.py
sarsolver/cxx_binding/__init__.py
sarsolver/cxx_binding/adjoint.py
sarsolver/cxx_binding/forward.py
sarsolver/cxx_binding/sarsolver_cxx.cpp
sarsolver/cxx_binding/sarsolver_cxx.py
sarsolver/io/__init__.py
sarsolver/io/cphd03.py
sarsolver/io/cphd101.py
sarsolver/numpy/__init__.py
sarsolver/numpy/hypothesis.py
sarsolver/numpy/measurement.py
sarsolver/numpy/operator.py
sarsolver/utils/__init__.py
sarsolver/utils/geodesy.py
sarsolver/utils/k_space.py
sarsolver/utils/misc.py
sarsolver/utils/signal.py
sarsolver.libs/libfftw3-5261d95d.so.3.6.10
sarsolver.libs/libgcc_s-0cd532bd.so.1
sarsolver.libs/libstdc++-5d72f927.so.6.0.33
sarsolver-1.0.4.dist-info/METADATA
sarsolver-1.0.4.dist-info/WHEEL
sarsolver-1.0.4.dist-info/top_level.txt
sarsolver-1.0.4.dist-info/RECORD
sarsolver-1.0.4.dist-info/licenses/LICENSE
