Metadata-Version: 2.4
Name: sarsolver
Version: 1.0.4
Summary: Python module with a compiled C++ backend used for Synthetic Aperture Radar (SAR) operator forward and adjoint evaluation. Compatible with CCPi's CIL framework by design.
Author-email: Joshua DM Hellier <joshuadmhellier@gmail.com>
License-Expression: Apache-2.0
Requires-Python: >=3.12
License-File: LICENSE
Requires-Dist: numpy<2.3.0,>=1.23.0
Requires-Dist: scipy<2.0.0,>=1.16.0
Requires-Dist: joblib<2.0.0,>=1.5.1
Requires-Dist: pymap3d<4.0.0,>=3.1.0
Requires-Dist: tqdm<5.0.0,>=4.67.1
Requires-Dist: sarpy<2.0.0,>=1.3.60
Requires-Dist: matplotlib<4.0.0,>=3.10.3
Requires-Dist: pytest<9.0.0,>=8.4.0
Dynamic: license-file
